{"chunk_definitions":[{"chunk_id":"csetup_chunk","chunk_label":"setup","document_id":"B142153A","expansion_state":0,"options":{"engine":"r","include":false,"label":"setup"},"row":9,"row_count":1,"visible":true},{"chunk_id":"crppjfbm7sk5j","chunk_label":"Initital_Loading","document_id":"B142153A","expansion_state":0,"options":{"echo":false,"engine":"r","label":"Initital_Loading","message":false,"warning":false},"row":19,"row_count":1,"visible":true},{"chunk_id":"cjxe0gxqajtqp","chunk_label":"unnamed-chunk-1","document_id":"B142153A","expansion_state":0,"options":{"engine":"r","label":"unnamed-chunk-6"},"row":29,"row_count":1,"visible":true}],"default_chunk_options":{"echo":true,"error":false},"doc_write_time":1560426877,"working_dir":null}